{
  "timeZone": "Asia/Tokyo",
  "dependencies": {
    "enabledAdvancedServices": [
      {
        "userSymbol": "Classroom",
        "version": "v1",
        "serviceId": "classroom"
      }
    ]
  },
  "exceptionLogging": "STACKDRIVER",
  "runtimeVersion": "V8",
  "oauthScopes": [
    "https://www.googleapis.com/auth/spreadsheets",
    "https://www.googleapis.com/auth/script.external_request",
    "https://www.googleapis.com/auth/classroom.coursework.students",
    "https://www.googleapis.com/auth/classroom.courses",
    "https://www.googleapis.com/auth/classroom.rosters",
    "https://www.googleapis.com/auth/classroom.coursework.me",
    "https://www.googleapis.com/auth/classroom.announcements",
    "https://www.googleapis.com/auth/classroom.profile.emails"
  ],
  "webapp": {
    "executeAs": "USER_DEPLOYING",
    "access": "MYSELF"
  }
}
